devqubit_braket/__init__.py
devqubit_braket/adapter.py
devqubit_braket/circuits.py
devqubit_braket/device.py
devqubit_braket/envelope.py
devqubit_braket/execution.py
devqubit_braket/py.typed
devqubit_braket/results.py
devqubit_braket/serialization.py
devqubit_braket/utils.py
devqubit_braket-0.1.10.dist-info/METADATA
devqubit_braket-0.1.10.dist-info/WHEEL
devqubit_braket-0.1.10.dist-info/entry_points.txt
devqubit_braket-0.1.10.dist-info/licenses/LICENSE
devqubit_braket-0.1.10.dist-info/RECORD
