Metadata-Version: 2.4
Name: devqubit-braket
Version: 0.1.10
Summary: devqubit adapter for Braket
Author: devqubit
License-Expression: Apache-2.0
License-File: LICENSE
Keywords: braket,experiment-tracking,quantum
Classifier: Development Status :: 3 - Alpha
Classifier: License :: OSI Approved :: Apache Software License
Classifier: Operating System :: OS Independent
Classifier: Programming Language :: Python :: 3
Classifier: Programming Language :: Python :: 3 :: Only
Classifier: Programming Language :: Python :: 3.11
Classifier: Programming Language :: Python :: 3.12
Classifier: Programming Language :: Python :: 3.13
Requires-Python: <3.14,>=3.11
Requires-Dist: amazon-braket-sdk<2,>=1.107
Requires-Dist: devqubit-engine<0.2.0,>=0.1.10
